<Properties StartupConfiguration="{32D0602F-1E6F-084D-B2AD-E9FAF79A17F0}|">
  <MonoDevelop.Ide.Workbench ActiveDocument="Assets/Challenge 1/Scripts/PlayerControllerX.cs">
    <Files>
      <File FileName="Assets/Scripts/PlayerController.cs" Line="23" Column="83" />
      <File FileName="Assets/Scripts/FollowPlayer.cs" Line="18" Column="65" />
      <File FileName="Assets/Challenge 1/Scripts/FollowPlayerX.cs" Line="8" Column="49" />
      <File FileName="Assets/Challenge 1/Scripts/PlayerControllerX.cs" Line="27" Column="88" />
    </Files>
    <Pads>
      <Pad Id="ProjectPad">
        <State name="__root__">
          <Node name="Prototype1" expanded="True">
            <Node name="Assets" expanded="True">
              <Node name="Challenge 1" expanded="True">
                <Node name="Scripts" expanded="True">
                  <Node name="PlayerControllerX.cs" selected="True" />
                </Node>
              </Node>
              <Node name="Scripts" expanded="True" />
            </Node>
          </Node>
        </State>
      </Pad>
    </Pads>
  </MonoDevelop.Ide.Workbench>
  <MonoDevelop.Ide.DebuggingService.PinnedWatches />
  <MonoDevelop.Ide.Workspace ActiveConfiguration="Debug" />
  <MonoDevelop.Ide.ItemProperties.Assembly-CSharp PreferredExecutionTarget="e914424c-ad05-46d1-8070-366f6b8db070" />
  <MonoDevelop.Ide.DebuggingService.Breakpoints>
    <BreakpointStore />
  </MonoDevelop.Ide.DebuggingService.Breakpoints>
  <MultiItemStartupConfigurations />
</Properties>